visbrain/__init__.py
visbrain/_pyqt_module.py
visbrain/config.py
visbrain/data_url.json
visbrain/gui/__init__.py
visbrain/gui/brain/__init__.py
visbrain/gui/brain/brain.py
visbrain/gui/brain/cbar.py
visbrain/gui/brain/user.py
visbrain/gui/brain/visuals.py
visbrain/gui/brain/interface/__init__.py
visbrain/gui/brain/interface/ui_init.py
visbrain/gui/brain/interface/gui/__init__.py
visbrain/gui/brain/interface/gui/brain_gui.py
visbrain/gui/brain/interface/ui_elements/__init__.py
visbrain/gui/brain/interface/ui_elements/ui_atlas.py
visbrain/gui/brain/interface/ui_elements/ui_config.py
visbrain/gui/brain/interface/ui_elements/ui_connectivity.py
visbrain/gui/brain/interface/ui_elements/ui_elements.py
visbrain/gui/brain/interface/ui_elements/ui_menu.py
visbrain/gui/brain/interface/ui_elements/ui_objects.py
visbrain/gui/brain/interface/ui_elements/ui_pictures.py
visbrain/gui/brain/interface/ui_elements/ui_screenshot.py
visbrain/gui/brain/interface/ui_elements/ui_sources.py
visbrain/gui/brain/interface/ui_elements/ui_timeseries.py
visbrain/gui/brain/interface/ui_elements/ui_vectors.py
visbrain/gui/figure/__init__.py
visbrain/gui/figure/figure.py
visbrain/gui/signal/__init__.py
visbrain/gui/signal/signal.py
visbrain/gui/signal/visuals.py
visbrain/gui/signal/gui/__init__.py
visbrain/gui/signal/gui/signal_gui.py
visbrain/gui/signal/ui_elements/__init__.py
visbrain/gui/signal/ui_elements/ui_annotations.py
visbrain/gui/signal/ui_elements/ui_elements.py
visbrain/gui/signal/ui_elements/ui_grid.py
visbrain/gui/signal/ui_elements/ui_init.py
visbrain/gui/signal/ui_elements/ui_menu.py
visbrain/gui/signal/ui_elements/ui_settings.py
visbrain/gui/signal/ui_elements/ui_signals.py
visbrain/gui/sleep/__init__.py
visbrain/gui/sleep/sleep.py
visbrain/gui/sleep/interface/__init__.py
visbrain/gui/sleep/interface/ui_init.py
visbrain/gui/sleep/interface/gui/__init__.py
visbrain/gui/sleep/interface/gui/sleep_gui.py
visbrain/gui/sleep/interface/ui_elements/__init__.py
visbrain-0.4.5.dist-info/LICENSE
visbrain-0.4.5.dist-info/METADATA
visbrain-0.4.5.dist-info/WHEEL
visbrain-0.4.5.dist-info/top_level.txt
visbrain-0.4.5.dist-info/RECORD
