Metadata-Version: 2.1
Name: visbrain
Version: 0.4.5
Summary: Hardware-accelerated visualization suite for brain-data in Python
Home-page: http://visbrain.org/
Author: Visbrain developpers
Author-email: e.combrisson@gmail.com
Maintainer: Etienne Combrisson
License: BSD 3-Clause License
Download-URL: https://github.com/EtienneCmb/visbrain/archive/v0.4.5.tar.gz
Keywords: brain MNI GPU visualization data OpenGL vispy neuroscience sleep data-mining
Platform: any
Classifier: Development Status :: 3 - Alpha
Classifier: Intended Audience :: Science/Research
Classifier: Intended Audience :: Education
Classifier: Intended Audience :: Developers
Classifier: Topic :: Scientific/Engineering :: Visualization
Classifier: Programming Language :: Python :: 3.5
Classifier: Programming Language :: Python :: 3.6
Classifier: Programming Language :: Python :: 3.7
Classifier: Operating System :: MacOS
Classifier: Operating System :: POSIX :: Linux
Classifier: Operating System :: Microsoft :: Windows
Classifier: Natural Language :: English
Requires-Dist: numpy (>=1.13)
Requires-Dist: scipy
Requires-Dist: vispy (>=0.5.3)
Requires-Dist: matplotlib (>=1.5.5)
Requires-Dist: pyqt5
Requires-Dist: pillow
Requires-Dist: PyOpenGL
Provides-Extra: full
Requires-Dist: mne ; extra == 'full'
Requires-Dist: tensorpac ; extra == 'full'
Requires-Dist: pandas ; extra == 'full'
Requires-Dist: xlrd ; extra == 'full'
Requires-Dist: scikit-image ; extra == 'full'
Requires-Dist: nibabel ; extra == 'full'
Requires-Dist: imageio ; extra == 'full'
Provides-Extra: roi
Requires-Dist: pandas ; extra == 'roi'
Requires-Dist: xlrd ; extra == 'roi'
Provides-Extra: sleep
Requires-Dist: mne ; extra == 'sleep'
Requires-Dist: tensorpac ; extra == 'sleep'
Provides-Extra: topo
Requires-Dist: scikit-image ; extra == 'topo'
